eastpy/__init__.py
eastpy/movies.py
eastpy-0.1.1.dist-info/DESCRIPTION.rst
eastpy-0.1.1.dist-info/METADATA
eastpy-0.1.1.dist-info/metadata.json
eastpy-0.1.1.dist-info/RECORD
eastpy-0.1.1.dist-info/top_level.txt
eastpy-0.1.1.dist-info/WHEEL
