Metadata-Version: 2.0
Name: eastpy
Version: 0.1.1
Summary: East-oriented Python examples, based on James Ladd's "East-oriented" technique.
Home-page: https://github.com/elgertam/eastpy
Author: Andrew M Elgert
Author-email: andrew.elgert@gmail.com
License: ISCL
Keywords: eastpy
Platform: UNKNOWN
Classifier: Development Status :: 2 - Pre-Alpha
Classifier: Intended Audience :: Developers
Classifier: License :: OSI Approved :: ISC License (ISCL)
Classifier: Natural Language :: English
Classifier: Programming Language :: Python :: 3
Classifier: Programming Language :: Python :: 3.3
Classifier: Programming Language :: Python :: 3.4
Classifier: Programming Language :: Python :: 3.5
Requires-Dist: attrs (>=15.0.0)
Requires-Dist: typing (>=3.5.0)
